carps
