Metadata-Version: 2.4
Name: carps
Version: 1.0.0
Summary: CARP-S: Benchmarking N Optimizers on M Benchmarks
Author-email: Carolin Benjamins <c.benjamins@ai.uni-hannover.de>
License: 
Project-URL: documentation, https://github.com/automl/CARP-S/
Project-URL: source, https://github.com/automl/CARP-S/
Classifier: Intended Audience :: Science/Research
Classifier: Intended Audience :: Developers
Classifier: License :: OSI Approved :: BSD License
Classifier: Programming Language :: Python
Classifier: Topic :: Software Development
Classifier: Topic :: Scientific/Engineering
Classifier: Operating System :: POSIX
Classifier: Operating System :: Unix
Classifier: Programming Language :: Python :: 3
Classifier: Programming Language :: Python :: 3.9
Classifier: Programming Language :: Python :: 3.10
Requires-Python: >=3.9
License-File: LICENSE
License-File: AUTHORS.md
Requires-Dist: autorank
Requires-Dist: ConfigSpace>=1.0.0
Requires-Dist: cryptography
Requires-Dist: dataclasses-json
Requires-Dist: domdf_python_tools
Requires-Dist: fire
Requires-Dist: hydra-colorlog
Requires-Dist: hydra-core
Requires-Dist: hydra-joblib-launcher
Requires-Dist: hydra-submitit-launcher
Requires-Dist: omegaconf
Requires-Dist: pandas
Requires-Dist: pyarrow
Requires-Dist: rich
Requires-Dist: seaborn
Requires-Dist: tomli
Requires-Dist: typing_extensions
Requires-Dist: pymoo
Requires-Dist: fire
Requires-Dist: ipywidgets
Requires-Dist: py-experimenter>=1.4.1
Provides-Extra: dev
Requires-Dist: pre-commit; extra == "dev"
Requires-Dist: ruff; extra == "dev"
Requires-Dist: mypy; extra == "dev"
Requires-Dist: mkdocs; extra == "dev"
Requires-Dist: mkdocs-material; extra == "dev"
Requires-Dist: mkdocs-autorefs; extra == "dev"
Requires-Dist: mkdocs-gen-files; extra == "dev"
Requires-Dist: mkdocs-literate-nav; extra == "dev"
Requires-Dist: mkdocs-glightbox; extra == "dev"
Requires-Dist: mkdocstrings[python]; extra == "dev"
Requires-Dist: markdown-exec[ansi]; extra == "dev"
Requires-Dist: mike; extra == "dev"
Requires-Dist: pillow; extra == "dev"
Requires-Dist: cairosvg; extra == "dev"
Requires-Dist: black; extra == "dev"
Requires-Dist: pytest; extra == "dev"
Requires-Dist: pytest-coverage; extra == "dev"
Requires-Dist: pytest-cases; extra == "dev"
Requires-Dist: pytest-xdist; extra == "dev"
Provides-Extra: containers
Requires-Dist: GitPython; extra == "containers"
Requires-Dist: py-experimenter>=1.4.1; extra == "containers"
Requires-Dist: pymysql; extra == "containers"
Dynamic: license-file
